mate/__init__.py
mate/__main__.py
mate/__version__.py
mate/config.py
mate/libs/__init__.py
mate/libs/mate_hookspecs.py
mate/modules/__init__.py
mate/modules/core.py
mate/modules/internal/__init__.py
mate/modules/internal/mate_find.py
mate/modules/internal/mate_help.py
mate/modules/internal/mate_plugins.py
mate/modules/internal/mate_show.py
mate/utils/__init__.py
mate/utils/colors.py
mate/utils/exceptions.py
mate/utils/logger.py
mate_shell-0.0.1.dist-info/LICENSE
mate_shell-0.0.1.dist-info/METADATA
mate_shell-0.0.1.dist-info/WHEEL
mate_shell-0.0.1.dist-info/entry_points.txt
mate_shell-0.0.1.dist-info/top_level.txt
mate_shell-0.0.1.dist-info/RECORD
