Metadata-Version: 2.1
Name: mate-shell
Version: 0.0.1
Summary: UNKNOWN
Home-page: https://github.com/twisted-fun/mate
Author: r00t3r
License: GPL
Project-URL: Source Code, https://github.com/twisted-fun/mate
Project-URL: Documentation, https://github.com/twisted-fun/mate/README.md
Platform: UNKNOWN
Classifier: Programming Language :: Python :: 3.6
Classifier: Programming Language :: Python :: 3.7
Requires-Python: >=3.6
Requires-Dist: colorama
Requires-Dist: docstring-parser
Requires-Dist: ipython
Requires-Dist: pluggy (<1.0,>=0.3)
Requires-Dist: prompt-toolkit (>=2.0.8)
Requires-Dist: rich
Requires-Dist: sentry-sdk
